maxhk/__init__.py
maxhk/credentials.py
maxhk/op.py
maxhk-0.1.1.dist-info/LICENSE
maxhk-0.1.1.dist-info/WHEEL
maxhk-0.1.1.dist-info/METADATA
maxhk-0.1.1.dist-info/RECORD
